[
  {
    "model_id": "prakosoee/indobert-food-quality-cls",
    "author": "unknown",
    "title": "prakosoee/indobert-food-quality-cls",
    "downloads": 0,
    "likes": 0,
    "tags": [
      "safetensors",
      "bert",
      "indobert",
      "aspect-based-sentiment-analysis",
      "sentiment-analysis",
      "text-classification",
      "id",
      "base_model:indobenchmark/indobert-base-p2",
      "base_model:finetune:indobenchmark/indobert-base-p2",
      "license:mit",
      "region:us"
    ],
    "pipeline_tag": "text-classification",
    "library": "",
    "created_at": "2026-01-11T07:41:01.000Z",
    "last_modified": "2026-01-11T08:19:37.000Z",
    "days_since_creation": 0,
    "url": "https://huggingface.co/prakosoee/indobert-food-quality-cls",
    "date": "2026-01-11",
    "source": "huggingface_model",
    "type": "model",
    "research_score": 0.4
  }
]