{
  "date": "2026-04-26T12:53:33.605447",
  "patterns": {
    "vision_systems": [
      {
        "title": "Mariobilly/z-image-rhea-2250",
        "url": "https://huggingface.co/Mariobilly/z-image-rhea-2250"
      },
      {
        "title": "Mariobilly/z-image-rhea-1500",
        "url": "https://huggingface.co/Mariobilly/z-image-rhea-1500"
      },
      {
        "title": "Mariobilly/z-image-turbo-msch-gbph",
        "url": "https://huggingface.co/Mariobilly/z-image-turbo-msch-gbph"
      },
      {
        "title": "Mariobilly/z-image-turbo-msch-cinema01",
        "url": "https://huggingface.co/Mariobilly/z-image-turbo-msch-cinema01"
      },
      {
        "title": "Mariobilly/z-image-turbo-a-clockwork-orange",
        "url": "https://huggingface.co/Mariobilly/z-image-turbo-a-clockwork-orange"
      },
      {
        "title": "Mariobilly/z-image-turbbo-the-shining",
        "url": "https://huggingface.co/Mariobilly/z-image-turbbo-the-shining"
      }
    ]
  },
  "inferences": [
    {
      "pattern": "vision_systems",
      "observation": "6 independent papers",
      "inference": "Strong convergence in Vision Systems - expect production adoption within 6-12 months",
      "confidence": "high"
    }
  ],
  "research_trends": [],
  "stats": {
    "total_patterns": 1,
    "total_inferences": 1,
    "total_papers": 6
  }
}